flake8_bitbucket
