Metadata-Version: 1.2
Name: flake8-bitbucket
Version: 0.1.10
Summary: A flake8 plugin for bitbucket insights.
Home-page: https://github.com/newAM/flake8-bitbucket
Author: Alex M.
Author-email: 7845120+newAM@users.noreply.github.com
License: MIT
Platform: UNKNOWN
Classifier: Environment :: Console
Classifier: Framework :: Flake8
Classifier: Intended Audience :: Developers
Classifier: License :: OSI Approved :: MIT License
Classifier: Programming Language :: Python :: 3 :: Only
Classifier: Programming Language :: Python :: 3.8
Classifier: Programming Language :: Python
Classifier: Topic :: Software Development :: Libraries :: Python Modules
Classifier: Topic :: Software Development :: Quality Assurance
Requires-Python: >=3.8
